{"albums":[{"album_name":"What's Your Pleasure?","artist_name":"Jessie Ware","play_count":673,"rank":1,"image":"album_what_s_your_pleasure.webp"},{"album_name":"Melt My Eyez See Your Future","artist_name":"Denzel Curry","play_count":453,"rank":2},{"album_name":"I LAY DOWN MY LIFE FOR YOU","artist_name":"JPEGMAFIA","play_count":367,"rank":3},{"album_name":"Wallsocket","artist_name":"underscores","play_count":355,"rank":4},{"album_name":"I LAY DOWN MY LIFE FOR YOU: DIRECTOR'S CUT","artist_name":"JPEGMAFIA","play_count":353,"rank":5},{"album_name":"Lianne La Havas","artist_name":"Lianne La Havas","play_count":332,"rank":6},{"album_name":"Since I Left You","artist_name":"The Avalanches","play_count":331,"rank":7},{"album_name":"Black On Both Sides","artist_name":"Mos Def","play_count":297,"rank":8},{"album_name":"4eva Is A Mighty Long Time","artist_name":"Big K.R.I.T.","play_count":297,"rank":9},{"album_name":"Atrocity Exhibition","artist_name":"Danny Brown","play_count":287,"rank":10},{"album_name":"Cheat Codes","artist_name":"Danger Mouse","play_count":285,"rank":11},{"album_name":"I Robot","artist_name":"The Alan Parsons Project","play_count":272,"rank":12},{"album_name":"Piñata","artist_name":"Freddie Gibbs","play_count":258,"rank":13},{"album_name":"The Forever Story","artist_name":"JID","play_count":257,"rank":14},{"album_name":"good kid, m.A.A.d city","artist_name":"Kendrick Lamar","play_count":228,"rank":15},{"album_name":"To Pimp A Butterfly","artist_name":"Kendrick Lamar","play_count":225,"rank":16},{"album_name":"Haram","artist_name":"Armand Hammer","play_count":224,"rank":17},{"album_name":"OFFLINE!","artist_name":"JPEGMAFIA","play_count":221,"rank":18},{"album_name":"Late Registration","artist_name":"Kanye West","play_count":216,"rank":19},{"album_name":"Enter The Wu-Tang (36 Chambers) [Expanded Edition]","artist_name":"Wu-Tang Clan","play_count":215,"rank":20}],"artists":[{"artist_name":"Kanye West","play_count":1179,"rank":1,"image":"artist_kanye_west.webp"},{"artist_name":"JPEGMAFIA","play_count":1086,"rank":2},{"artist_name":"Kendrick Lamar","play_count":922,"rank":3},{"artist_name":"Jessie Ware","play_count":794,"rank":4},{"artist_name":"Denzel Curry","play_count":756,"rank":5},{"artist_name":"Danny Brown","play_count":636,"rank":6},{"artist_name":"Fiona Apple","play_count":594,"rank":7},{"artist_name":"Freddie Gibbs","play_count":585,"rank":8},{"artist_name":"JID","play_count":584,"rank":9},{"artist_name":"A Tribe Called Quest","play_count":475,"rank":10},{"artist_name":"Sufjan Stevens","play_count":469,"rank":11},{"artist_name":"Logic","play_count":396,"rank":12},{"artist_name":"Travis Scott","play_count":395,"rank":13},{"artist_name":"The Avalanches","play_count":390,"rank":14},{"artist_name":"underscores","play_count":389,"rank":15},{"artist_name":"A$AP Rocky","play_count":371,"rank":16},{"artist_name":"Tyler, The Creator","play_count":358,"rank":17},{"artist_name":"The Roots","play_count":356,"rank":18},{"artist_name":"Lianne La Havas","play_count":332,"rank":19},{"artist_name":"Fleet Foxes","play_count":322,"rank":20}],"tracks":[{"album_name":"Begin Again","track_name":"Begin Again","artist_name":"Jessie Ware","play_count":102,"rank":1,"image":"track_begin_again.webp"},{"album_name":"What's Your Pleasure?","track_name":"In Your Eyes","artist_name":"Jessie Ware","play_count":98,"rank":2},{"album_name":"What's Your Pleasure?","track_name":"Remember Where You Are","artist_name":"Jessie Ware","play_count":86,"rank":3},{"album_name":"What's Your Pleasure?","track_name":"The Kill","artist_name":"Jessie Ware","play_count":84,"rank":4},{"album_name":"I LAY DOWN MY LIFE FOR YOU","track_name":"either on or off the drugs","artist_name":"JPEGMAFIA","play_count":82,"rank":5},{"album_name":"What's Your Pleasure?","track_name":"Soul Control","artist_name":"Jessie Ware","play_count":78,"rank":6},{"album_name":"Lianne La Havas","track_name":"Weird Fishes","artist_name":"Lianne La Havas","play_count":76,"rank":7},{"album_name":"Live At Electric Lady","track_name":"Endtroduction - Live At Electric Lady","artist_name":"Denzel Curry","play_count":75,"rank":8},{"album_name":"OFFLINE!","track_name":"HAZARD DUTY PAY!","artist_name":"JPEGMAFIA","play_count":67,"rank":9},{"album_name":"I LAY DOWN MY LIFE FOR YOU: DIRECTOR'S CUT","track_name":"PROTECT THE CROSS","artist_name":"JPEGMAFIA","play_count":66,"rank":10},{"album_name":"Wallsocket","track_name":"Duhhhhhhhhhhhhhhhhh","artist_name":"underscores","play_count":66,"rank":11},{"album_name":"Take Me To Your Leader","track_name":"I Wonder","artist_name":"King Geedorah","play_count":64,"rank":12},{"album_name":"Melt My Eyez See Your Future","track_name":"Chrome Hearts [Feat. Zacari]","artist_name":"Denzel Curry","play_count":64,"rank":13},{"album_name":"4eva Is A Mighty Long Time","track_name":"Aux Cord","artist_name":"Big K.R.I.T.","play_count":63,"rank":14},{"album_name":"Wallsocket","track_name":"Uncanny long arms (with Jane Remover)","artist_name":"underscores","play_count":63,"rank":15},{"album_name":"Since I Left You","track_name":"Two Hearts In 3/4 Time","artist_name":"The Avalanches","play_count":61,"rank":16},{"album_name":"Melt My Eyez See Your Future","track_name":"Larger Than Life","artist_name":"Denzel Curry","play_count":61,"rank":17},{"album_name":"Since I Left You","track_name":"Live At Dominoes","artist_name":"The Avalanches","play_count":61,"rank":18},{"album_name":"Extraordinary Machine","track_name":"Waltz (Better Than Fine)","artist_name":"Fiona Apple","play_count":61,"rank":19},{"album_name":"We Won't Be Alone","track_name":"We Won't Be Alone","artist_name":"Feint","play_count":60,"rank":20}],"genres":[{"genre":"hip hop","play_count":9677,"rank":1,"image":"genre_hip_hop.webp"},{"genre":"conscious hip hop","play_count":4847,"rank":2},{"genre":"trap","play_count":4638,"rank":3},{"genre":"alternative hip hop","play_count":4451,"rank":4},{"genre":"boom bap","play_count":4413,"rank":5},{"genre":"pop rap","play_count":4245,"rank":6},{"genre":"abstract hip hop","play_count":3532,"rank":7},{"genre":"jazz rap","play_count":3491,"rank":8},{"genre":"experimental hip hop","play_count":3405,"rank":9},{"genre":"east coast hip hop","play_count":3333,"rank":10},{"genre":"alternative rock","play_count":2795,"rank":11},{"genre":"soul","play_count":2329,"rank":12},{"genre":"electronic","play_count":2283,"rank":13},{"genre":"contemporary r&b","play_count":2150,"rank":14},{"genre":"gangsta rap","play_count":2069,"rank":15},{"genre":"indie pop","play_count":1940,"rank":16},{"genre":"pop","play_count":1884,"rank":17},{"genre":"dance pop","play_count":1769,"rank":18},{"genre":"cloud rap","play_count":1677,"rank":19},{"genre":"indie rock","play_count":1562,"rank":20}]}